{"id": 741237, "name": "1200W Miner Switching Power Supply for GPU Rig Mining BTC ETH Ethereum 1200W DPS-1200FB A 438202-002 440785-001 For DL580G5 apw3", "shortName": "1200W Miner Switching Power Supply for GPU Rig Mining BTC ETH", "imageUrl": "https://c1.neweggimages.com/productimage/nb300/B1A6D2305210Y5TEW35.jpg", "brand": "", "description": "", "specs": {}, "slug": "1200w-miner-switching-power-supply-for-gpu-rig-mining-btc-eth-ethereum-1200w-dps-1200fb-a-438202-002-440785-001-for-dl58", "url": "https://www.newegg.ca/p/2S7-07JP-2V5S8", "retailer": "Newegg Canada", "category": "power-supplies", "currentPrice": 620.79, "minPrice": 620.79, "maxPrice": 620.79, "priceCount": 1, "firstSeen": "2026-04-06T07:27:47", "lastUpdated": "2026-04-06T07:27:47", "matchGroup": null, "canonicalId": null, "upc": "", "mpn": "", "priceComparison": []}