{"id": 158431, "name": "300Mbps Wireless Wall AP USB WiFi Router In Wall AP RJ45 802.3af POE WiFi Access Point with USB Charging Phone RJ11 On-off", "shortName": "300Mbps Wireless Wall AP USB WiFi Router In Wall AP RJ45 802.3af POE", "imageUrl": "https://c1.neweggimages.com/productimage/nb300/AN4W_1_20200419132239813.jpg", "brand": "Generic", "description": "In-wall WiFi access point with POE power and USB charging for integrated home network deployment.", "specs": {"speed": "300Mbps", "standards": "802.11n", "power": "802.3af POE", "connections": "RJ45/RJ11"}, "slug": "300mbps-wireless-wall-ap-usb-wifi-router-in-wall-ap-rj45-8023af-poe-wifi-access-point-with-usb-charging-phone-rj11-on-of", "url": "https://www.newegg.ca/p/0E6-01GC-005E3", "retailer": "Newegg Canada", "category": "routers", "currentPrice": 67.82, "minPrice": 67.82, "maxPrice": 67.82, "priceCount": 1, "firstSeen": "2026-03-15T04:07:44", "lastUpdated": "2026-03-15T04:07:44", "matchGroup": null, "canonicalId": 15279, "upc": "", "mpn": "", "priceComparison": []}