{"id": 379563, "name": "Acer Vero B7 B247Y E 23.8\" IPS Monitor - 1920x1080 - 100Hz Refresh Rate - 4ms GTG - FreeSync - 99% sRGB - HDMI 1.4 - VGA - DisplayPort 1.2 - Headphone Jack - Built-in Speakers (UM.QB7AA.E01)", "shortName": "Acer Vero B7 B247Y E 23.8\" IPS Monitor - 1920x1080 - 100Hz Refresh", "imageUrl": "https://d2po40yubr0dlz.cloudfront.net/images/products/vuugo-acer-UM.QB7AA.E01-300x300.jpg", "brand": "Acer", "description": "23.8-inch FHD IPS monitor with 100Hz refresh rate and AMD FreeSync for gaming and productivity.", "specs": {"screen_size": "23.8\"", "resolution": "1920x1080", "panel_type": "IPS", "response_time": "4ms", "color_gamut": "99% sRGB", "refresh_rate": "100Hz", "adaptive_sync": "AMD FreeSync", "connectivity": ["HDMI 1.4", "VGA", "DisplayPort 1.2", "USB 3.0"]}, "slug": "acer-vero-b7-b247y-e-238-ips-monitor-1920x1080-100hz-refresh-rate-4ms-gtg-freesync-99-srgb-hdmi-14-vga-displayport-12-he", "url": "https://www.vuugo.com/product/acer-vero-b7-umqb7aae01/", "retailer": "Vuugo", "category": "monitors", "currentPrice": 171.68, "minPrice": 171.68, "maxPrice": 171.68, "priceCount": 1, "firstSeen": "2026-03-23T04:43:58", "lastUpdated": "2026-03-23T04:43:58", "matchGroup": null, "canonicalId": 18761, "upc": "", "mpn": "UM.QB7AA.E01", "priceComparison": []}