{"id": 14062, "name": "AMD Ryzen Threadripper 7980X 350W SP6 - Zen 4 64-Core/128-Threads (100-100001350WOF)", "shortName": "AMD Ryzen Threadripper 7980X 350W SP6 - Zen 4 64-Core/128-Threads", "imageUrl": "https://c1.neweggimages.com/productimage/nb300/19-113-808-02.jpg", "brand": "AMD", "description": "High-end 64-core processor for workstations and content creators requiring maximum multi-threaded performance.", "specs": {"brand": "AMD", "series": "Ryzen Threadripper", "generation": "7000", "cores": 64, "threads": 128, "architecture": "Zen 4", "socket": "SP6", "tdp": "350W"}, "slug": "amd-ryzen-threadripper-7980x-350w-sp6-zen-4-64-core128-threads-100-100001350wof", "url": "https://www.newegg.ca/amd-ryzen-threadripper-7000-series-ryzen-threadripper-7980x-storm-peak-socket-str5-desktop-cpu-processor/p/N82E16819113808", "retailer": "Newegg Canada", "category": "cpus", "currentPrice": 6799.99, "minPrice": 6799.99, "maxPrice": 7399.99, "priceCount": 12, "firstSeen": "2026-03-09T08:04:32", "lastUpdated": "2026-04-06T07:05:26", "matchGroup": null, "canonicalId": 689, "upc": "", "mpn": "100-100001350WOF", "priceComparison": [{"id": 382318, "retailer": "Vuugo", "price": 7369.26, "url": "https://www.vuugo.com/product/amd-ryzen-threadripper-100-100001350wof/", "slug": "amd-ryzen-threadripper-7980x-32ghz-processor-socket-str5-64-cores-128-threads-256mb-l3-cache-64mb-l2-cache-350w-tdp-51gh"}]}