{"id": 57923, "name": "APEVIA Jupiter Series ATX-JP600W 600 W ATX12V SLI CrossFire 80 PLUS BRONZE Certified Power Supply", "shortName": "APEVIA Jupiter Series ATX-JP600W 600 W ATX12V SLI CrossFire 80 PLUS", "imageUrl": "https://c1.neweggimages.com/productimage/nb300/AMB1S200129RODrN.jpg", "brand": "(46)", "description": "600W ATX power supply with 80 Plus Bronze efficiency and SLI/CrossFire support for gaming.", "specs": {"wattage": "600W", "form_factor": "ATX", "efficiency": "80 Plus Bronze", "sli_crossfire": "Yes"}, "slug": "apevia-jupiter-series-atx-jp600w-600-w-atx12v-sli-crossfire-80-plus-bronze-certified-power-supply", "url": "https://www.newegg.ca/apevia-corp-jupiter-series-atx12v-600-w-80-plus-bronze-certified-power-supply-atx-jp600w/p/N82E16817148058", "retailer": "Newegg Canada", "category": "power-supplies", "currentPrice": 131.04, "minPrice": 131.04, "maxPrice": 131.04, "priceCount": 1, "firstSeen": "2026-03-10T04:54:39", "lastUpdated": "2026-03-10T04:54:39", "matchGroup": null, "canonicalId": 7540, "upc": "", "mpn": "ATX-JP600W", "priceComparison": []}