{"id": 232268, "name": "ARMOURY Ryzen 7 9800X3D RX 9070 XT 64GB RAM 4TB SSD W11P", "shortName": "ARMOURY Ryzen 7 9800X3D RX 9070 XT 64GB RAM 4TB SSD W11P", "imageUrl": "https://ccimg1.canadacomputers.com/Products/brand/23066.jpg", "brand": "logo ARMOURY", "description": "Extreme gaming workstation with Ryzen 7 9800X3D and Radeon RX 9070 XT with 64GB RAM for ultra-demanding applications.", "specs": {"cpu": "AMD Ryzen 7 9800X3D", "gpu": "RX 9070 XT", "ram": "64GB", "storage": "4TB SSD", "os": "Windows 11 Pro"}, "slug": "armoury-ryzen-7-9800x3d-rx-9070-xt-64gb-ram-4tb-ssd-w11p", "url": "https://www.canadacomputers.com/en/armoury-gaming-desktops/265647/armoury-ryzen-7-9800x3d-rx-9070-xt-64gb-ram-4tb-ssd-w11p-rtaru00275.html", "retailer": "Canada Computers", "category": "desktops", "currentPrice": 3899.0, "minPrice": 3899.0, "maxPrice": 4299.0, "priceCount": 2, "firstSeen": "2026-03-16T05:51:28", "lastUpdated": "2026-03-16T23:48:11", "matchGroup": null, "canonicalId": 15911, "upc": "", "mpn": "", "priceComparison": []}