{"id": 382690, "name": "ASUS ROG STRIX 1000W Gold Aura Edition Fully Modular Power Supply - 80 PLUS Gold Certified - ATX 3.0 - 135mm Axial-tech Fan - ROG Heatsinks - PCIe 5.0 12VHPWR GPU Cable - 4x PCI-E 6+2-Pin Connectors (ROG-STRIX-1000G-AURA-GAMING)", "shortName": "ASUS ROG STRIX 1000W Gold Aura Edition Fully Modular Power Supply", "imageUrl": "https://d2po40yubr0dlz.cloudfront.net/images/products/vuugo-asus-ROG-STRIX-1000G-AURA-GAM-300x300.png", "brand": "ASUS", "description": "1000W gaming-focused fully modular power supply with RGB support for enthusiast builds.", "specs": {"wattage": "1000W", "certification": "80 PLUS Gold", "modular": "Fully Modular", "atx_version": "ATX 3.0", "pcie_gen": "5.0", "fan_size": "135mm", "pcie_connectors": "4x 6+2-pin"}, "slug": "asus-rog-strix-1000w-gold-aura-edition-fully-modular-power-supply-80-plus-gold-certified-atx-30-135mm-axial-tech-fan-rog", "url": "https://www.vuugo.com/product/asus-rog-strix-rog-strix-1000g-aura-gam/", "retailer": "Vuugo", "category": "power-supplies", "currentPrice": 301.4, "minPrice": 300.3, "maxPrice": 304.7, "priceCount": 8, "firstSeen": "2026-03-23T04:52:38", "lastUpdated": "2026-04-10T02:17:57", "matchGroup": null, "canonicalId": 20964, "upc": "", "mpn": "ROG-STRIX-1000G-AURA-GAMING", "priceComparison": []}