{"id": 8248, "name": "ASUS ROG Azoth 75 Wireless DIY Custom Gaming Keyboard, OLED display, Gasket-Mount, Three-Layer Dampening, Hot-Swappable Pre-lubed ROG NX Snow Switches & Keyboard Stabilizers, PBT Keycaps, RGB", "shortName": "ASUS ROG Azoth 75 Wireless DIY Custom Gaming Keyboard, OLED display", "imageUrl": "https://c1.neweggimages.com/productimage/nb300/23-193-151-03.jpg", "brand": "ASUS", "description": "An ASUS ROG 75% DIY custom gaming keyboard with OLED display and hot-swappable switches for builders.", "specs": {"form_factor": "75%", "type": "mechanical", "switches": "ROG NX Snow", "connection": "wireless", "feature": "OLED display", "keycaps": "PBT", "backlit": "RGB"}, "slug": "asus-rog-azoth-75-wireless-diy-custom-gaming-keyboard-oled-display-gasket-mount-three-layer-dampening-hot-swappable-pre-", "url": "https://www.newegg.ca/asus-rog-azoth-rog-nx-snow-mechanical-switches-gunmetal/p/N82E16823193151", "retailer": "Newegg Canada", "category": "keyboards", "currentPrice": 870.99, "minPrice": 677.99, "maxPrice": 870.99, "priceCount": 5, "firstSeen": "2026-03-08T13:03:01", "lastUpdated": "2026-03-15T03:43:42", "matchGroup": null, "canonicalId": 12280, "upc": "", "mpn": "ASUS-ROG-AZOTH-75", "priceComparison": []}