{"id": 246426, "name": "ASUS Vivobook Windows Laptop 15.6\" Intel Core 5-120U 16GB 512GB Windows 11 Home, F1504VAP-WH56", "shortName": "ASUS Vivobook Windows Laptop 15.6\" Intel Core 5-120U 16GB 512GB", "imageUrl": "https://ccimg1.canadacomputers.com/Products/250x250/135/4186/9k0sm824fvw/95751.jpg", "brand": "ASUS", "description": "Portable 15.6-inch Windows laptop with Intel Core 5 processor and 16GB RAM for everyday computing and light work.", "specs": {"screen_size": "15.6\"", "processor": "Intel Core 5-120U", "ram": "16GB", "storage": "512GB", "os": "Windows 11 Home", "color": "White", "model": "F1504VAP-WH56"}, "slug": "asus-vivobook-windows-laptop-156-intel-core-5-120u-16gb-512gb-windows-11-home-f1504vap-wh56", "url": "", "retailer": "Canada Computers", "category": "laptops", "currentPrice": 300.0, "minPrice": 300.0, "maxPrice": 300.0, "priceCount": 1, "firstSeen": "2026-03-16T11:33:18", "lastUpdated": "2026-03-16T11:33:18", "matchGroup": null, "canonicalId": 11850, "upc": "", "mpn": "F1504VAP-WH56", "priceComparison": []}