{"id": 67270, "name": "ASUS ExpertWiFi EBG19P 8 ports PoE+ Gigabit VPN wired router", "shortName": "ASUS ExpertWiFi EBG19P 8 ports PoE+ Gigabit VPN wired router", "imageUrl": "https://ccimg1.canadacomputers.com/Products/250x250/5798/5110/259350/31436438.jpg", "brand": "ASUS", "description": "An 8-port Gigabit wired business router with PoE+ and VPN capabilities.", "specs": {"ports": "8", "port_type": "Gigabit", "poe": true, "vpn": true, "type": "Wired Router"}, "slug": "asus-expertwifi-ebg19p-8-ports-poe-gigabit-vpn-wired-router", "url": "https://www.canadacomputers.com/en/wired-vpn-security-routers/259350/asus-expertwifi-ebg19p-8-ports-poe-gigabit-vpn-wired-router-ebg19p.html", "retailer": "Canada Computers", "category": "network-switches", "currentPrice": 249.99, "minPrice": 249.99, "maxPrice": 249.99, "priceCount": 2, "firstSeen": "2026-03-10T13:09:22", "lastUpdated": "2026-03-10T18:35:05", "matchGroup": null, "canonicalId": 8592, "upc": "197105071285", "mpn": "EBG19P", "priceComparison": []}