{"id": 32451, "name": "ASUS Prime Z690-P D4 LGA 1700 (Intel\u00ae 12th&13th Gen) ATX motherboard (PCIe 5.0,DDR4,14+1 Power Stages, 3x M.2,2.5Gb LAN,V-M.2 e-key,front panel USB 3.2 Gen 1 USB Type-C\u00ae,Thunderbolt\u2122 4 support)", "shortName": "ASUS Prime Z690-P D4 LGA 1700 (Intel\u00ae 12th&13th Gen) ATX motherboard", "imageUrl": "https://c1.neweggimages.com/productimage/nb300/13-119-511-V01.jpg", "brand": "ASUS", "description": "ASUS Prime Z690-P D4 ATX motherboard for Intel 12th-13th gen with DDR4, PCIe 5.0, and Thunderbolt 4 support.", "specs": {"socket": "LGA 1700", "chipset": "Z690", "form_factor": "ATX", "memory": "DDR4", "pcie": "5.0", "m2_slots": 3}, "slug": "asus-prime-z690-p-d4-lga-1700-intel-12th13th-gen-atx-motherboard-pcie-50ddr4141-power-stages-3x-m225gb-lanv-m2-e-keyfron", "url": "https://www.newegg.ca/asus-prime-z690-p-d4-atx-intel-motherboard-intel-z690-lga-1700-designed-with-dual-mounting-holes-compatible-with-both-intel-lga1700-and-lga1200-cooling-brackets/p/N82E16813119511", "retailer": "Newegg Canada", "category": "motherboards", "currentPrice": 317.12, "minPrice": 307.75, "maxPrice": 457.75, "priceCount": 7, "firstSeen": "2026-03-09T14:52:09", "lastUpdated": "2026-04-06T07:13:39", "matchGroup": null, "canonicalId": 1003, "upc": "", "mpn": "PRIME-Z690-P-D4", "priceComparison": []}