{"id": 59687, "name": "ASUS TUF GAMING B760M-PLUS II - Motherboard - micro ATX - LGA1700 Socket - B760 Chipset - USB 3.2 Gen 1, USB 3.2 Gen 2,", "shortName": "ASUS TUF GAMING B760M-PLUS II - Motherboard - micro ATX - LGA1700", "imageUrl": "https://c1.neweggimages.com/productimage/nb300/AFYUD24041018QQPXB4.jpg", "brand": "ASUS", "description": "Gaming-focused micro-ATX B760M motherboard for Intel LGA 1700 with enhanced power delivery.", "specs": {"socket": "LGA 1700", "chipset": "B760", "form_factor": "mATX", "usb_gen1": true, "usb_gen2": true}, "slug": "asus-tuf-gaming-b760m-plus-ii-motherboard-micro-atx-lga1700-socket-b760-chipset-usb-32-gen-1-usb-32-gen-2", "url": "https://www.newegg.ca/asus-90mb1hd0-m0eay0-motherboards-amd/p/2MG-000B-006B7", "retailer": "Newegg Canada", "category": "motherboards", "currentPrice": 421.9, "minPrice": 421.9, "maxPrice": 421.9, "priceCount": 2, "firstSeen": "2026-03-10T05:00:42", "lastUpdated": "2026-03-11T16:23:17", "matchGroup": null, "canonicalId": 1899, "upc": "", "mpn": "TUF-GAMING-B760M-PLUS-II-MOTHERBOARD", "priceComparison": []}