{"id": 378694, "name": "ASUS TUF Gaming VG34VQ3B 34\" Curved VA LED Monitor - 3440x1440 - 1500R Curvature - 180Hz Refresh Rate - 1ms MPRT - 90% DCI-P3 - HDR - FreeSync Premium - 2x HDMI 2.0 - 2x DisplayPort 1.2 - USB 3.2 Gen1 Hub - Built-in 2W Speakers - Headphone Jack (VG34VQ3B)", "shortName": "ASUS TUF Gaming VG34VQ3B 34\" Curved VA LED Monitor - 3440x1440", "imageUrl": "https://d2po40yubr0dlz.cloudfront.net/images/products/vuugo-asus-VG34VQ3B-300x300.png", "brand": "ASUS", "description": "ASUS TUF Gaming 34-inch ultrawide curved monitor with 3440x1440 resolution and 180Hz refresh rate for competitive gaming.", "specs": {"size": "34\"", "resolution": "3440x1440", "panel_type": "VA", "refresh_rate": "180Hz", "response_time": "1ms MPRT", "curvature": "1500R", "color_gamut": "90% DCI-P3"}, "slug": "asus-tuf-gaming-vg34vq3b-34-curved-va-led-monitor-3440x1440-1500r-curvature-180hz-refresh-rate-1ms-mprt-90-dci-p3-hdr-fr", "url": "https://www.vuugo.com/product/asus-tuf-gaming-vg34vq3b/", "retailer": "Vuugo", "category": "monitors", "currentPrice": 466.4, "minPrice": 466.4, "maxPrice": 466.4, "priceCount": 1, "firstSeen": "2026-03-23T04:41:10", "lastUpdated": "2026-03-23T04:41:10", "matchGroup": null, "canonicalId": 3788, "upc": "", "mpn": "VG34VQ3B", "priceComparison": [{"id": 8889, "retailer": "Newegg Canada", "price": 359.99, "url": "https://www.newegg.ca/asus-vg34vq3b-34-uwqhd-180-hz-tuf-gaming-va/p/N82E16824281324", "slug": "asus-tuf-gaming-34-ultrawide-qhd-2k-1440p-180hz-with-amd-freesync-premium-adaptive-sync-1ms-built-in-speakers-elmb-sync-"}]}