{"id": 381609, "name": "Axiom 16GB DDR5 4800MHz SoDIMM Memory Module for HP Compaq Victus 16t-d000 Notebooks - PC5-38400 - CL40 - 1.10V - 260-pin (4M9Y5AA-AX)", "shortName": "Axiom 16GB DDR5 4800MHz SoDIMM Memory Module for HP Compaq Victus", "imageUrl": "https://d2po40yubr0dlz.cloudfront.net/images/products/vuugo-axiom-4M9Y5AA-AX-300x300.jpg", "brand": "Axiom", "description": "16GB DDR5 4800MHz SoDIMM memory module designed for HP Compaq Victus 16t-d000 notebooks.", "specs": {"capacity": "16GB", "type": "DDR5", "speed": "4800MHz", "form_factor": "SoDIMM", "pins": 260, "voltage": "1.10V", "latency": "CL40"}, "slug": "axiom-16gb-ddr5-4800mhz-sodimm-memory-module-for-hp-compaq-victus-16t-d000-notebooks-pc5-38400-cl40-110v-260-pin-4m9y5aa", "url": "https://www.vuugo.com/product/axiom-16gb-ddr5-4m9y5aa-ax/", "retailer": "Vuugo", "category": "ram", "currentPrice": 517.19, "minPrice": 451.37, "maxPrice": 520.4, "priceCount": 13, "firstSeen": "2026-03-23T04:49:31", "lastUpdated": "2026-04-11T04:01:31", "matchGroup": null, "canonicalId": 20236, "upc": "", "mpn": "4M9Y5AA-AX", "priceComparison": []}