{"id": 199556, "name": "BenQ 27\" Full HD 1080P 100Hz IPS Ultra Slim Bezel, TUV-Certified Flicker-Free, Low Blue Light Plus Computer Monitor GW2791", "shortName": "BenQ 27\" Full HD 1080P 100Hz IPS Ultra Slim Bezel, TUV-Certified", "imageUrl": "https://c1.neweggimages.com/productimage/nb300/24-014-979-08.jpg", "brand": "(2)", "description": "BenQ 27\" Full HD 100Hz IPS monitor with ultra-slim bezel, flicker-free technology, and low blue light for comfortable viewing.", "specs": {"size": "27\"", "resolution": "Full HD 1080P", "refresh_rate": "100Hz", "panel": "IPS", "features": "Ultra Slim Bezel, Flicker-Free, Low Blue Light"}, "slug": "benq-27-full-hd-1080p-100hz-ips-ultra-slim-bezel-tuv-certified-flicker-free-low-blue-light-plus-computer-monitor-gw2791", "url": "https://www.newegg.ca/benq-gw2791-27-fhd-100-hz-ips/p/N82E16824014979", "retailer": "Newegg Canada", "category": "monitors", "currentPrice": 139.99, "minPrice": 139.99, "maxPrice": 139.99, "priceCount": 1, "firstSeen": "2026-03-15T19:09:36", "lastUpdated": "2026-03-15T19:09:36", "matchGroup": null, "canonicalId": 6455, "upc": "", "mpn": "GW2791", "priceComparison": [{"id": 53974, "retailer": "Newegg Canada", "price": 139.99, "url": "https://www.newegg.ca/benq-gw2791-27-fhd-100-hz-ips/p/N82E16824014979", "slug": "benq-27-full-hd-1080p-100hz-ips-hdmi-displayport-ultra-slim-bezel-tuv-certified-flicker-free-low-blue-light-plus-compute"}]}