{"id": 55813, "name": "Bluetooth Wireless Mouse, Transparent RGB Mechanical Dual Mode Gaming Mouse, A Must-Have Cool USB Computer Mouse for Gaming and Esports", "shortName": "Bluetooth Wireless Mouse, Transparent RGB Mechanical Dual Mode Gaming", "imageUrl": "https://c1.neweggimages.com/productimage/nb300/B7VES2309170YZBSSC1.jpg", "brand": "Bluetooth", "description": "Transparent mechanical dual-mode wireless gaming mouse with RGB lighting for gaming and esports.", "specs": {"connectivity": "Bluetooth/USB", "lighting": "RGB", "design": "Mechanical Transparent", "purpose": "Gaming/Esports"}, "slug": "bluetooth-wireless-mouse-transparent-rgb-mechanical-dual-mode-gaming-mouse-a-must-have-cool-usb-computer-mouse-for-gamin", "url": "https://www.newegg.ca/p/32K-01E2-00016", "retailer": "Newegg Canada", "category": "mice", "currentPrice": 74.99, "minPrice": 74.99, "maxPrice": 74.99, "priceCount": 1, "firstSeen": "2026-03-10T04:47:08", "lastUpdated": "2026-03-10T04:47:08", "matchGroup": null, "canonicalId": 14057, "upc": "", "mpn": "", "priceComparison": []}