{"id": 8286, "name": "Cooler Master MS110 Combo Bundle with Mem-chanical Gaming Keyboard and Gaming Mouse with Optical Sensor", "shortName": "Cooler Master MS110 Combo Bundle with Mem-chanical Gaming Keyboard", "imageUrl": "https://c1.neweggimages.com/productimage/nb300/23-129-104-S01.jpg", "brand": "Cooler Master", "description": "A combo bundle featuring a mechanical gaming keyboard and optical mouse, ideal for gamers seeking an affordable complete peripheral package.", "specs": {"bundle": "Keyboard + Mouse", "switch_type": "Mechanical", "mouse_sensor": "Optical"}, "slug": "cooler-master-ms110-combo-bundle-with-mem-chanical-gaming-keyboard-and-gaming-mouse-with-optical-sensor", "url": "https://www.newegg.ca/black-cooler-master-ms110-mem-chanical-switch/p/N82E16823129104", "retailer": "Newegg Canada", "category": "keyboards", "currentPrice": 86.99, "minPrice": 86.99, "maxPrice": 86.99, "priceCount": 12, "firstSeen": "2026-03-08T13:03:09", "lastUpdated": "2026-03-11T16:06:43", "matchGroup": null, "canonicalId": 3688, "upc": "", "mpn": "MS110", "priceComparison": []}