{"id": 161589, "name": "Cudy 24-Port Gigabit Unmanaged Switch GS1024", "shortName": "Cudy 24-Port Gigabit Unmanaged Switch GS1024", "imageUrl": "https://c1.neweggimages.com/productimage/nb300/33-939-002-03.png", "brand": "Cudy", "description": "A 24-port unmanaged gigabit switch for cost-effective network expansion without management features.", "specs": {"ports": 24, "speed": "Gigabit", "type": "Unmanaged", "model": "GS1024"}, "slug": "cudy-24-port-gigabit-unmanaged-switch-gs1024", "url": "https://www.newegg.ca/cudy-gs1024-3-0-managed-fixed-configuration-24-x-rj45/p/N82E16833939002", "retailer": "Newegg Canada", "category": "network-switches", "currentPrice": 109.99, "minPrice": 109.99, "maxPrice": 109.99, "priceCount": 1, "firstSeen": "2026-03-15T04:27:12", "lastUpdated": "2026-03-15T04:27:12", "matchGroup": null, "canonicalId": 10811, "upc": "", "mpn": "GS1024", "priceComparison": []}