{"id": 379049, "name": "Dell UltraSharp U2725QE 27\" 4K UHD LED IPS Monitor - 3840x2160 - 120Hz Refresh Rate - 5ms GTG - Ambient Light Sensor - 2x DisplayPort 1.4 - HDMI 2.1 - Thunderbolt 4 (DP 1.4) with 140W PD - USB-C (USB 10Gbps KVM) Upstream - 2.5GbE Ethernet (DELL-U2725QE)", "shortName": "Dell UltraSharp U2725QE 27\" 4K UHD LED IPS Monitor - 3840x2160", "imageUrl": "https://d2po40yubr0dlz.cloudfront.net/images/products/vuugo-dell-DELL-U2725QE-300x300.jpg", "brand": "Dell", "description": "27-inch 4K UHD IPS monitor with 120Hz refresh rate, Thunderbolt 4, and USB-C for professional creative work.", "specs": {"screen_size": "27\"", "resolution": "3840x2160", "panel_type": "IPS", "refresh_rate": "120Hz", "response_time": "5ms GTG", "features": "Thunderbolt 4"}, "slug": "dell-ultrasharp-u2725qe-27-4k-uhd-led-ips-monitor-3840x2160-120hz-refresh-rate-5ms-gtg-ambient-light-sensor-2x-displaypo", "url": "https://www.vuugo.com/product/dell-ultrasharp-u2725qe-dell-u2725qe/", "retailer": "Vuugo", "category": "monitors", "currentPrice": 1097.49, "minPrice": 1097.49, "maxPrice": 1097.49, "priceCount": 1, "firstSeen": "2026-03-23T04:42:37", "lastUpdated": "2026-03-23T04:42:37", "matchGroup": null, "canonicalId": 1933, "upc": "884116484578", "mpn": "U2725QE", "priceComparison": [{"id": 62578, "retailer": "Canada Computers", "price": 1337.49, "url": "https://www.canadacomputers.com/en/monitors/275241/dell-ultrasharp-27-4k-thunderbolt-hub-monitor-u2725qe-dell-u2725qe.html", "slug": "dell-ultrasharp-27-4k-thunderbolt-hub-monitor-u2725qe"}]}