{"id": 592155, "name": "FRACTAL DESIGN NORTH XL RC White", "shortName": "FRACTAL DESIGN NORTH XL RC White", "imageUrl": "https://ccimg1.canadacomputers.com/Products/250x250/213/5596/270999/68589.jpeg", "brand": "FRACTAL", "description": "", "specs": {}, "slug": "fractal-design-north-xl-rc-white", "url": "https://www.canadacomputers.com/en/full-tower-cases/270999/fractal-design-north-xl-rc-white-fd-c-nor1x-06.html", "retailer": "Canada Computers", "category": "cases", "currentPrice": 269.99, "minPrice": 269.99, "maxPrice": 269.99, "priceCount": 1, "firstSeen": "2026-03-28T14:25:59", "lastUpdated": "2026-03-28T14:25:59", "matchGroup": null, "canonicalId": null, "upc": "", "mpn": "", "priceComparison": []}