{"id": 376977, "name": "GIGABYTE Radeon RX 6800 GAMING OC 16G Video Card - 16GB 256-bit GDDR6 - 2155MHz Boost Core Clock - PCI Express 4.0 - FreeSync - 2x HDMI 2.1 - 2x DisplayPort 1.4 - RGB Fusion 2.0 - Protection Metal Backplate (GV-R68GAMING OC-16GD)", "shortName": "GIGABYTE Radeon RX 6800 GAMING OC 16G Video Card - 16GB 256-bit GDDR6", "imageUrl": "https://d2po40yubr0dlz.cloudfront.net/images/products/vuugo-gigabyte-GV-R68GAMING_OC-16GD82-300x300.png", "brand": "Gigabyte", "description": "", "specs": {}, "slug": "gigabyte-radeon-rx-6800-gaming-oc-16g-video-card-16gb-256-bit-gddr6-2155mhz-boost-core-clock-pci-express-40-freesync-2x-", "url": "https://www.vuugo.com/product/gigabyte-radeon-rx-gv-r68gaming-oc-16gd/", "retailer": "Vuugo", "category": "gpus", "currentPrice": 842.46, "minPrice": 842.46, "maxPrice": 842.46, "priceCount": 1, "firstSeen": "2026-03-23T04:36:56", "lastUpdated": "2026-03-23T04:36:56", "matchGroup": null, "canonicalId": null, "upc": "", "mpn": "", "priceComparison": []}