{"id": 6954, "name": "HP 230 Wireless Mouse and Keyboard Combo", "shortName": "HP 230 Wireless Mouse and Keyboard Combo", "imageUrl": "https://ccimg1.canadacomputers.com/Products/250x250/276/224253/07488.jpg", "brand": "HP", "description": "Wireless keyboard and mouse combo in black for office and home use.", "specs": {"type": "combo", "connectivity": "wireless", "color": "black", "model": "230"}, "slug": "hp-230-wireless-mouse-and-keyboard-combo", "url": "https://www.canadacomputers.com/en/home-office-keyboard-and-mouse-combos/224253/hp-230-wireless-mouse-and-keyboard-combo-18h24aaaba.html", "retailer": "Canada Computers", "category": "keyboards", "currentPrice": 29.99, "minPrice": 29.99, "maxPrice": 32.99, "priceCount": 51, "firstSeen": "2026-03-08T12:51:20", "lastUpdated": "2026-03-13T16:55:34", "matchGroup": null, "canonicalId": 13083, "upc": "196337618886", "mpn": "", "priceComparison": []}