{"id": 179228, "name": "iCAN M3 Black Tri-Mode 58g Lightweight Gaming Mouse for eSports", "shortName": "iCAN M3 Black Tri-Mode 58g Lightweight Gaming Mouse for eSports", "imageUrl": "https://ccimg1.canadacomputers.com/Products/250x250/1563/1675/272480/05165.jpg", "brand": "iCAN", "description": "Lightweight tri-mode wireless gaming mouse designed for esports professionals and competitive players.", "specs": {"brand": "iCAN", "model": "M3", "type": "tri-mode wireless mouse", "color": "black", "weight": "58g"}, "slug": "ican-m3-black-tri-mode-58g-lightweight-gaming-mouse-for-esports", "url": "https://www.canadacomputers.com/en/gaming-mice/272480/ican-m3-black-tri-mode-58g-lightweight-gaming-mouse-for-esports-m3-black.html", "retailer": "Canada Computers", "category": "mice", "currentPrice": 42.99, "minPrice": 42.99, "maxPrice": 42.99, "priceCount": 1, "firstSeen": "2026-03-15T14:03:59", "lastUpdated": "2026-03-15T14:03:59", "matchGroup": null, "canonicalId": 15769, "upc": "", "mpn": "", "priceComparison": []}