{"id": 114862, "name": "iCAN Premium Series Gaming Chair, Black(Open Box)", "shortName": "iCAN Premium Series Gaming Chair, Black(Open Box)", "imageUrl": "https://ccimg1.canadacomputers.com/Products/250x250/916/1047/130389/23829.jpg", "brand": "iCAN", "description": "Premium black gaming chair engineered for superior comfort and durability.", "specs": {"series": "premium", "color": "black", "type": "gaming chair", "condition": "open box"}, "slug": "ican-premium-series-gaming-chair-blackopen-box", "url": "https://www.canadacomputers.com/en/gaming-chair/204702/ican-premium-series-gaming-chair-black-lx9001.html", "retailer": "Canada Computers", "category": "accessories", "currentPrice": 196.99, "minPrice": 196.99, "maxPrice": 205.99, "priceCount": 2, "firstSeen": "2026-03-13T17:09:53", "lastUpdated": "2026-03-26T02:21:07", "matchGroup": null, "canonicalId": 9533, "upc": "1931930117768", "mpn": "PREMIUM-SERIES", "priceComparison": []}