{"id": 742082, "name": "In Win Z Series Micro-ATX Mini Tower Chassis Z589CQ450TB3", "shortName": "In Win Z Series Micro-ATX Mini Tower Chassis Z589CQ450TB3", "imageUrl": "https://c1.neweggimages.com/productimage/nb300/A6ZPD2603260H4MQY23.jpg", "brand": "In", "description": "", "specs": {}, "slug": "in-win-z-series-micro-atx-mini-tower-chassis-z589cq450tb3", "url": "https://www.newegg.ca/in-win-micro-atx-cases/p/2AM-001H-00240", "retailer": "Newegg Canada", "category": "cases", "currentPrice": 323.99, "minPrice": 323.99, "maxPrice": 323.99, "priceCount": 1, "firstSeen": "2026-04-06T07:30:55", "lastUpdated": "2026-04-06T07:30:55", "matchGroup": null, "canonicalId": null, "upc": "", "mpn": "", "priceComparison": []}