{"id": 658518, "name": "Intel Core i7-9700F Coffee Lake Desktop Processor i7 9th Gen, 8-Core up to 4.7 GHz Turbo LGA 1151 (300 Series) 65W BX80684i79700F Without Graphics", "shortName": "Intel Core i7-9700F Coffee Lake Desktop Processor i7 9th Gen, 8-Core", "imageUrl": "https://c1.neweggimages.com/productimage/nb300/BD50S2206090RB142DA.jpg", "brand": "Intel", "description": "", "specs": {}, "slug": "intel-core-i7-9700f-coffee-lake-desktop-processor-i7-9th-gen-8-core-up-to-47-ghz-turbo-lga-1151-300-series-65w-bx80684i7", "url": "https://www.newegg.ca/p/2MN-0004-008X0", "retailer": "Newegg Canada", "category": "cpus", "currentPrice": 395.89, "minPrice": 395.89, "maxPrice": 395.89, "priceCount": 1, "firstSeen": "2026-04-01T02:27:10", "lastUpdated": "2026-04-01T02:27:10", "matchGroup": null, "canonicalId": null, "upc": "", "mpn": "", "priceComparison": []}