{"id": 57452, "name": "Intel Core i3 9th Gen - Core i3-9100F Coffee Lake 4-Core 3.6 GHz (4.2 GHz Turbo) LGA 1151 (300 Series) 65W BX80684i39100F Desktop Processor Without Graphics- OEM", "shortName": "Intel Core i3 9th Gen - Core i3-9100F Coffee Lake 4-Core 3.6 GHz (4.2", "imageUrl": "https://c1.neweggimages.com/productimage/nb300/AYTVS2303240C9P9T91.jpg", "brand": "Intel", "description": "Intel Core i3-9100F budget-friendly quad-core processor for basic computing and light gaming.", "specs": {"brand": "Intel Core i3", "generation": "9th Gen", "series": "Coffee Lake", "cores": "4-Core", "base_clock": "3.6 GHz", "boost_clock": "4.2 GHz", "socket": "LGA 1151", "tdp": "65W", "graphics": "None", "model": "i3-9100F"}, "slug": "intel-core-i3-9th-gen-core-i3-9100f-coffee-lake-4-core-36-ghz-42-ghz-turbo-lga-1151-300-series-65w-bx80684i39100f-deskto", "url": "https://www.newegg.ca/p/274-000A-01NA0", "retailer": "Newegg Canada", "category": "cpus", "currentPrice": 235.4, "minPrice": 235.4, "maxPrice": 235.4, "priceCount": 2, "firstSeen": "2026-03-10T04:53:03", "lastUpdated": "2026-03-11T16:15:44", "matchGroup": null, "canonicalId": 1573, "upc": "", "mpn": "CORE-I3-9100F", "priceComparison": [{"id": 57317, "retailer": "Newegg Canada", "price": 158.6, "url": "https://www.newegg.ca/intel-core-i3-9th-gen-core-i3-9100f-coffee-lake-lga-1151-processors-desktops/p/274-000A-01MF7", "slug": "refurbishedintel-core-i3-9100f-coffee-lake-4-core-36-ghz-42-ghz-turbo-lga-1151-300-series-65w-bx80684i39100f-desktop-pro"}]}