{"id": 194123, "name": "Juniper Networks EX Series EX2300-48P - switch - 48 ports - managed - rack-mountable EX2300-48P", "shortName": "Juniper Networks EX Series EX2300-48P - switch - 48 ports - managed", "imageUrl": "https://c1.neweggimages.com/productimage/nb300/BGATS22101816ZCK4BB.jpg", "brand": "Juniper", "description": "A managed rack-mountable Layer 2/3 switch with 48 Gigabit ports and SFP uplinks.", "specs": {"model": "EX2300-48P", "ports": 48, "speed": "Gigabit", "mounting": "Rack-mountable", "series": "EX"}, "slug": "juniper-networks-ex-series-ex2300-48p-switch-48-ports-managed-rack-mountable-ex2300-48p", "url": "https://www.newegg.ca/juniper-ex2300-48p/p/0XP-005R-002F5", "retailer": "Newegg Canada", "category": "network-switches", "currentPrice": 2445.1, "minPrice": 2445.1, "maxPrice": 2445.1, "priceCount": 1, "firstSeen": "2026-03-15T14:53:58", "lastUpdated": "2026-03-15T14:53:58", "matchGroup": null, "canonicalId": 11266, "upc": "", "mpn": "EX2300-48P", "priceComparison": []}