{"id": 53499, "name": "Lenovo 5210 1.92TB 2.5\" SATA Hot Swappable Internal SSD 4XB7A38144", "shortName": "Lenovo 5210 1.92TB 2.5\" SATA Hot Swappable", "imageUrl": "https://c1.neweggimages.com/productimage/nb300/V1DSD210130Z6M9V.jpg", "brand": "Lenovo", "description": "Server-grade 1.92TB hot-swap SATA SSD for enterprise infrastructure.", "specs": {"capacity": "1.92TB", "form_factor": "2.5 inch", "interface": "SATA", "type": "hot-swap"}, "slug": "lenovo-5210-192tb-25-sata-hot-swappable-internal-ssd-4xb7a38144", "url": "https://www.newegg.ca/lenovo-1-92tb-5210/p/1B4-001H-02EK7", "retailer": "Newegg Canada", "category": "ssds", "currentPrice": 523.0, "minPrice": 523.0, "maxPrice": 523.0, "priceCount": 2, "firstSeen": "2026-03-10T04:38:59", "lastUpdated": "2026-03-11T16:01:44", "matchGroup": null, "canonicalId": 6268, "upc": "", "mpn": "4XB7A38144", "priceComparison": []}