{"id": 7484, "name": "Lenovo V15 G4 15.6\" Intel i3-1315U 16GB 512GB Win11H", "shortName": "Lenovo V15 G4 15.6\" Intel i3-1315U 16GB 512GB Win11H", "imageUrl": "https://ccimg1.canadacomputers.com/Products/250x250/135/4186/281844/06041.jpg", "brand": "Lenovo", "description": "Lenovo 15.6\" budget laptop with Intel Core i3 processor for basic computing tasks.", "specs": {"screen_size": "15.6\"", "processor": "Intel i3-1315U", "ram": "16GB", "storage": "512GB", "os": "Windows 11 Home"}, "slug": "lenovo-v15-g4-156-intel-i3-1315u-16gb-512gb-win11h", "url": "https://www.canadacomputers.com/en/windows-laptops/281844/lenovo-v15-g4-15-6-intel-i3-1315u-16gb-512gb-win11h-83a100pbus.html", "retailer": "Canada Computers", "category": "laptops", "currentPrice": 599.0, "minPrice": 599.0, "maxPrice": 599.0, "priceCount": 25, "firstSeen": "2026-03-08T12:53:09", "lastUpdated": "2026-03-12T01:07:19", "matchGroup": null, "canonicalId": 13146, "upc": "198155714429", "mpn": "", "priceComparison": []}