{"id": 150911, "name": "Lenovo 12 TB 3.5\" Internal Hard Drive - Near Line SAS (NL-SAS) - 7200rpm - Hot Swappable", "shortName": "Lenovo 12 TB 3.5\" Internal Hard Drive - Near Line SAS - 7200rpm - Hot", "imageUrl": "https://c1.neweggimages.com/productimage/nb300/A98C_1_201805071647226378.jpg", "brand": "Lenovo", "description": "Lenovo 12TB 3.5\" hot-swappable NL-SAS hard drive for nearline storage.", "specs": {"capacity": "12TB", "form_factor": "3.5\"", "interface": "NL-SAS", "rpm": "7200", "type": "Hot Swappable"}, "slug": "lenovo-12-tb-35-internal-hard-drive-near-line-sas-nl-sas-7200rpm-hot-swappable", "url": "https://www.newegg.ca/p/1YU-0027-00078", "retailer": "Newegg Canada", "category": "hard-drives", "currentPrice": 1030.71, "minPrice": 1030.71, "maxPrice": 1030.71, "priceCount": 1, "firstSeen": "2026-03-15T03:38:36", "lastUpdated": "2026-03-15T03:38:36", "matchGroup": null, "canonicalId": 15163, "upc": "", "mpn": "", "priceComparison": []}