{"id": 56135, "name": "Lenovo ThinkPad T14s Gen 6 14\" Touchscreen Notebook - Intel Core Ultra 7 268V (2.20 GHz) - 32 GB - 512 GB SSD - Windows 11 Pro - Intel Arc Graphics 140V - Webcam - Wi-Fi 7 (21QX00LBUS)", "shortName": "Lenovo ThinkPad T14s Gen 6 14\" Touchscreen Notebook - Intel Core", "imageUrl": "", "brand": "Lenovo", "description": "A 14-inch touchscreen business laptop with Intel Core Ultra 7 processor, 32GB RAM, and Windows 11 Pro for professionals.", "specs": {"screen_size": "14\"", "screen_type": "Touchscreen", "processor": "Intel Core Ultra 7 268V", "ram": "32GB", "storage": "512GB SSD", "os": "Windows 11 Pro", "graphics": "Intel Arc Graphics 140V", "connectivity": "Wi-Fi 7"}, "slug": "lenovo-thinkpad-t14s-gen-6-14-touchscreen-notebook-intel-core-ultra-7-268v-220-ghz-32-gb-512-gb-ssd-windows-11-pro-intel", "url": "https://www.newegg.ca/lenovo-14-0-arc-graphics-140v/p/1TS-000E-1DV39", "retailer": "Newegg Canada", "category": "laptops", "currentPrice": 3479.22, "minPrice": 3479.22, "maxPrice": 3479.22, "priceCount": 1, "firstSeen": "2026-03-10T04:48:20", "lastUpdated": "2026-03-10T04:48:20", "matchGroup": null, "canonicalId": 1338, "upc": "", "mpn": "21QX00LBUS", "priceComparison": []}