{"id": 379156, "name": "LG UltraGear 27G850A-B 27\" UHD 4K Nano IPS Black Gaming Monitor - 3840X2160 Dual-Mode (4K 240Hz / FHD 480Hz) - 1ms GTG - DisplayHDR 600 - G-SYNC Compatible - FreeSync Premium Pro - DisplayPort 2.1 - 2x HDMI 2.1 - USB 3.2 Gen1 Hub - Headphone-out", "shortName": "LG UltraGear 27G850A-B 27\" UHD 4K Nano IPS Black Gaming Monitor", "imageUrl": "https://d2po40yubr0dlz.cloudfront.net/images/products/vuugo-lg-27G850A-B-300x300.jpg", "brand": "LG", "description": "27-inch 4K gaming monitor with 240Hz refresh rate and G-SYNC/FreeSync support for high-performance gaming.", "specs": {"screen_size": "27\"", "resolution": "3840x2160", "panel_type": "Nano IPS", "refresh_rate": "240Hz (4K) / 480Hz (FHD)", "response_time": "1ms GTG", "hdr": "DisplayHDR 600", "sync_tech": "G-SYNC Compatible, FreeSync Premium Pro"}, "slug": "lg-ultragear-27g850a-b-27-uhd-4k-nano-ips-black-gaming-monitor-3840x2160-dual-mode-4k-240hz-fhd-480hz-1ms-gtg-displayhdr", "url": "https://www.vuugo.com/product/lg-ultragear-27g850a-b-27g850a-b/", "retailer": "Vuugo", "category": "monitors", "currentPrice": 1055.98, "minPrice": 1055.98, "maxPrice": 1055.98, "priceCount": 1, "firstSeen": "2026-03-23T04:42:58", "lastUpdated": "2026-03-23T04:42:58", "matchGroup": null, "canonicalId": null, "upc": "", "mpn": "", "priceComparison": []}