{"id": 54727, "name": "Logitech Signature Slim MK955 for Business Wireless Keyboard and Mouse Combo", "shortName": "Logitech Signature Slim MK955 for Business Wireless Keyboard and", "imageUrl": "https://c1.neweggimages.com/productimage/nb300/0GA-0001-01132-11.jpg", "brand": "Logitech", "description": "Slim professional wireless keyboard and mouse combo for business users.", "specs": {"type": "Combo", "connectivity": "Wireless", "target": "Business", "model": "MK955"}, "slug": "logitech-signature-slim-mk955-for-business-wireless-keyboard-and-mouse-combo", "url": "https://www.newegg.ca/p/0GA-0001-01132", "retailer": "Newegg Canada", "category": "keyboards", "currentPrice": 156.89, "minPrice": 149.99, "maxPrice": 156.89, "priceCount": 3, "firstSeen": "2026-03-10T04:43:24", "lastUpdated": "2026-03-15T03:42:56", "matchGroup": null, "canonicalId": 6758, "upc": "", "mpn": "MK955", "priceComparison": [{"id": 54733, "retailer": "Newegg Canada", "price": 149.99, "url": "https://www.newegg.ca/logitech-signature-slim-mk955-keypad-mouse-usb-type-a/p/N82E16823126761", "slug": "logitech-signature-slim-mk955-combo-for-business-copilot-edition-wireless-keyboard-and-mouse-graphite-920-013271"}]}