{"id": 376602, "name": "MSI GeForce RTX 4080 SUPER 16G VENTUS 3X OC Video Card - 16GB 256-bit GDDR6X - 2595MHz Extreme Performance Core Clock - PCI Express 4.0 - 2x HDMI 2.1a - 2x DisplayPort 1.4a - TORX FAN 4.0 - Metal Backplate (G4080S16V3C)", "shortName": "MSI GeForce RTX 4080 SUPER 16G VENTUS 3X OC Video Card - 16GB 256-bit", "imageUrl": "https://d2po40yubr0dlz.cloudfront.net/images/products/vuugo-msi-G4080S16V3C-300x300.png", "brand": "MSI", "description": "", "specs": {}, "slug": "msi-geforce-rtx-4080-super-16g-ventus-3x-oc-video-card-16gb-256-bit-gddr6x-2595mhz-extreme-performance-core-clock-pci-ex", "url": "https://www.vuugo.com/product/msi-geforce-rtx-g4080s16v3c/", "retailer": "Vuugo", "category": "gpus", "currentPrice": 1568.97, "minPrice": 1568.97, "maxPrice": 1568.97, "priceCount": 1, "firstSeen": "2026-03-23T04:36:01", "lastUpdated": "2026-03-23T04:36:01", "matchGroup": null, "canonicalId": 16543, "upc": "", "mpn": "RTX 4080 SUPER 16G VENTUS 3X OC VIDEO CARD", "priceComparison": []}