{"id": 32426, "name": "Open BoxASUS PRIME B860M-A WIFI-CSM B860 LGA 1851 mATX motherboard, Intel\u00ae Core\u2122 Ultra Series 2 Ready, Advanced AI PC-ready, 7+1+1+1 stage, DDR5, PCIe 5.0 x16, HDMI, USB 20Gbps Type-C\u00ae, 2x M.2, WiFi 6E, 2.5Gb", "shortName": "Open BoxASUS PRIME B860M-A WIFI-CSM B860 LGA 1851 mATX motherboard", "imageUrl": "https://c1.neweggimages.com/productimage/nb300/13-119-714-05.png", "brand": "ASUS", "description": "Open box compact mATX motherboard for Intel Core Ultra Series 2 with DDR5, PCIe 5.0, and WiFi 6E.", "specs": {"socket": "LGA 1851", "chipset": "B860", "formFactor": "mATX", "memory": "DDR5", "pciExpress": "5.0", "wifi": "WiFi 6E", "m2Slots": "2x", "condition": "Open Box"}, "slug": "open-boxasus-prime-b860m-a-wifi-csm-b860-lga-1851-matx-motherboard-intel-core-ultra-series-2-ready-advanced-ai-pc-ready-", "url": "https://www.newegg.ca/asus-prime-b860m-a-wifi-csm-micro-atx-motherboard-intel-b860-lga-1851/p/N82E16813119714R", "retailer": "Newegg Canada", "category": "motherboards", "currentPrice": 161.99, "minPrice": 161.99, "maxPrice": 161.99, "priceCount": 5, "firstSeen": "2026-03-09T14:52:09", "lastUpdated": "2026-03-11T16:21:45", "matchGroup": null, "canonicalId": 809, "upc": "", "mpn": "PRIME-B860M-A-WIFI-CSM-B860", "priceComparison": [{"id": 14632, "retailer": "Newegg Canada", "price": 239.99, "url": "https://www.newegg.ca/asus-prime-b860m-a-wifi-csm-micro-atx-motherboard-intel-b860-lga-1851/p/N82E16813119714", "slug": "asus-prime-b860m-a-wifi-csm-b860-lga-1851-matx-motherboard-intel-core-ultra-series-2-ready-advanced-ai-pc-ready-7111-sta"}]}