{"id": 382839, "name": "Phanteks AMP Series 750W Fully Modular Power Supply - 80 PLUS Gold Certified - 120mm Fluid Dynamic Bearing Fan - Hybrid Fanless Mode - 4x PCI-E 6+2-Pin Connectors (PH-P750G)", "shortName": "Phanteks AMP Series 750W Fully Modular Power Supply - 80 PLUS Gold", "imageUrl": "https://d2po40yubr0dlz.cloudfront.net/images/products/vuugo-phanteks-PH-P750G-300x300.jpg", "brand": "Phanteks", "description": "750W fully modular power supply with 80 PLUS Gold certification and hybrid fanless mode for gaming enthusiasts.", "specs": {"wattage": "750W", "certification": "80 PLUS Gold", "modular": "Fully Modular", "fanless_mode": "Hybrid", "pcie_connectors": "4x 6+2-pin"}, "slug": "phanteks-amp-series-750w-fully-modular-power-supply-80-plus-gold-certified-120mm-fluid-dynamic-bearing-fan-hybrid-fanles", "url": "https://www.vuugo.com/product/phanteks-amp-series-ph-p750g/", "retailer": "Vuugo", "category": "power-supplies", "currentPrice": 161.7, "minPrice": 161.7, "maxPrice": 161.7, "priceCount": 1, "firstSeen": "2026-03-23T04:53:01", "lastUpdated": "2026-03-23T04:53:01", "matchGroup": null, "canonicalId": 21063, "upc": "", "mpn": "PH-P750G", "priceComparison": []}