{"id": 160074, "name": "PHENOFICE High Performance USB Hub Hub Adapter for Computer Expansion Transfer Adapters", "shortName": "PHENOFICE High Performance USB Hub Hub Adapter for Computer Expansion", "imageUrl": "https://c1.neweggimages.com/productimage/nb300/BZPGD2509200HLUQQDE.jpg", "brand": "PHENOFICE", "description": "High-performance USB hub adapter for computer expansion and data transfer.", "specs": {"type": "hub adapter", "feature": "high performance"}, "slug": "phenofice-high-performance-usb-hub-hub-adapter-for-computer-expansion-transfer-adapters", "url": "https://www.newegg.ca/p/0J2-07ES-00AD1", "retailer": "Newegg Canada", "category": "accessories", "currentPrice": 128.99, "minPrice": 128.99, "maxPrice": 128.99, "priceCount": 1, "firstSeen": "2026-03-15T04:17:07", "lastUpdated": "2026-03-15T04:17:07", "matchGroup": null, "canonicalId": 15456, "upc": "", "mpn": "", "priceComparison": []}