{"id": 1693, "name": "PNY GeForce RTX\u2122 5060 GDDR7 Double Fans", "shortName": "PNY GeForce RTX\u2122 5060 GDDR7 Double Fans", "imageUrl": "https://ccimg1.canadacomputers.com/Products/250x250/10000/10041/286023/29761.jpg", "brand": "PNY", "description": "PNY GeForce RTX 5060 graphics card with GDDR7 memory and dual-fan cooling for mainstream gaming.", "specs": {"gpu": "GeForce RTX 5060", "memory": "GDDR7", "cooling": "Double Fans"}, "slug": "pny-geforce-rtx-5060-gddr7-double-fans", "url": "https://www.canadacomputers.com/en/powered-by-nvidia/286023/pny-geforce-rtx-5060-gddr7-double-fans-vcg50608dfxpb1.html", "retailer": "Canada Computers", "category": "gpus", "currentPrice": 537.99, "minPrice": 537.99, "maxPrice": 537.99, "priceCount": 3, "firstSeen": "2026-03-08T05:39:52", "lastUpdated": "2026-03-09T14:46:25", "matchGroup": null, "canonicalId": 2881, "upc": "751492797083", "mpn": "RTX5060-GDDR7", "priceComparison": []}