{"id": 741160, "name": "PSU For Seventeam 500W Switching Power Supply ST-500EAP FSP500-50HPN", "shortName": "PSU For Seventeam 500W Switching Power Supply ST-500EAP FSP500-50HPN", "imageUrl": "https://c1.neweggimages.com/productimage/nb300/B1A6D2303240YP9WZ83.jpg", "brand": "PSU", "description": "", "specs": {}, "slug": "psu-for-seventeam-500w-switching-power-supply-st-500eap-fsp500-50hpn", "url": "https://www.newegg.ca/p/2S7-07JP-2U1W0", "retailer": "Newegg Canada", "category": "power-supplies", "currentPrice": 915.98, "minPrice": 915.98, "maxPrice": 915.98, "priceCount": 1, "firstSeen": "2026-04-06T07:27:30", "lastUpdated": "2026-04-06T07:27:30", "matchGroup": null, "canonicalId": null, "upc": "", "mpn": "", "priceComparison": []}