{"id": 759959, "name": "Redragon M811-RGB Gaming Mouse(Open Box)", "shortName": "Redragon M811-RGB Gaming Mouse(Open Box)", "imageUrl": "https://ccimg1.canadacomputers.com/Products/250x250/1563/1675/236593/02813.jpg", "brand": "Redragon", "description": "", "specs": {}, "slug": "redragon-m811-rgb-gaming-mouseopen-box", "url": "https://www.canadacomputers.com/en/gaming-mice/246726/redragon-m811-rgb-gaming-mouse-m811-rgb.html", "retailer": "Canada Computers", "category": "mice", "currentPrice": 24.29, "minPrice": 24.29, "maxPrice": 24.29, "priceCount": 1, "firstSeen": "2026-04-07T02:30:28", "lastUpdated": "2026-04-07T02:30:28", "matchGroup": null, "canonicalId": null, "upc": "", "mpn": "", "priceComparison": []}