{"id": 737178, "name": "RefurbishedMSI A55-G35 AMD A55 Socket FM1 DDR3 ATX Motherboard", "shortName": "RefurbishedMSI A55-G35 AMD A55 Socket FM1 DDR3 ATX Motherboard", "imageUrl": "https://c1.neweggimages.com/productimage/nb300/ARA8D2405180A2UKO0C.jpg", "brand": "MSI", "description": "", "specs": {}, "slug": "refurbishedmsi-a55-g35-amd-a55-socket-fm1-ddr3-atx-motherboard", "url": "https://www.newegg.ca/msi-a55-g35-motherboards-amd-amd-a55-socket-fm1/p/2MG-000M-006Z2", "retailer": "Newegg Canada", "category": "motherboards", "currentPrice": 64.12, "minPrice": 64.12, "maxPrice": 64.12, "priceCount": 1, "firstSeen": "2026-04-06T07:11:22", "lastUpdated": "2026-04-06T07:11:22", "matchGroup": null, "canonicalId": null, "upc": "", "mpn": "", "priceComparison": []}