{"id": 54244, "name": "SAMSUNG Odyssey LS25BG402ENXGO G40B 25\" FHD Gaming Monitor, IPS, 240Hz, 1ms, G-Sync Compatible, AMD FreeSync Premium, HDR10, Ultrawide Game View, DisplayPort, HDMI, Fully Adjustable Stand", "shortName": "SAMSUNG Odyssey LS25BG402ENXGO G40B 25\" FHD Gaming Monitor, IPS", "imageUrl": "https://c1.neweggimages.com/productimage/nb300/24-027-110-12.jpg", "brand": "SAMSUNG", "description": "25\" FHD gaming monitor with 240Hz refresh rate and 1ms response time, designed for competitive gamers.", "specs": {"screen_size": "25\"", "resolution": "FHD", "refresh_rate": "240Hz", "response_time": "1ms", "panel_type": "IPS", "sync_tech": ["G-Sync Compatible", "AMD FreeSync Premium"]}, "slug": "samsung-odyssey-ls25bg402enxgo-g40b-25-fhd-gaming-monitor-ips-240hz-1ms-g-sync-compatible-amd-freesync-premium-hdr10-ult", "url": "https://www.newegg.ca/samsung-ls25bg402enxgo-25-fhd-240-hz-ips/p/N82E16824027110", "retailer": "Newegg Canada", "category": "monitors", "currentPrice": 479.0, "minPrice": 479.0, "maxPrice": 479.0, "priceCount": 2, "firstSeen": "2026-03-10T04:41:36", "lastUpdated": "2026-03-11T16:04:15", "matchGroup": 391, "canonicalId": 1301, "upc": "", "mpn": "25BG402E", "priceComparison": [{"id": 379637, "retailer": "Vuugo", "price": 278.62, "url": "https://www.vuugo.com/product/samsung-odyssey-g4-ls25bg402enxgo/", "slug": "samsung-odyssey-g4-25-fhd-ips-monitor-1920x1080-240hz-refresh-rate-1ms-gtg-freesync-premium-nvidia-g-sync-compatible-aut"}]}