{"id": 379731, "name": "Samsung LS27A400UJNXZA 27\" IPS Flat Monitor - 1920x1080 - 75Hz Max Refresh Rate - 5ms GTG - Fully Ergonomic Stand - USB Type-C with 65W PD - AMD FreeSync - DisplayPort 1.2 - HDMI 1.4 - Headphone Jack - 2x USB 3.0 - 2x USB 2.0", "shortName": "Samsung LS27A400UJNXZA 27\" IPS Flat Monitor - 1920x1080 - 75Hz Max", "imageUrl": "https://d2po40yubr0dlz.cloudfront.net/images/products/vuugo-samsung-LS27A400UJNXZA-300x300.jpg", "brand": "Samsung", "description": "27-inch flat IPS monitor with USB-C Power Delivery and AMD FreeSync for versatile computing.", "specs": {"screen_size": "27\"", "resolution": "1920x1080", "panel_type": "IPS", "refresh_rate": "75Hz", "response_time": "5ms", "adaptive_sync": "FreeSync", "usb_c_pd": "65W"}, "slug": "samsung-ls27a400ujnxza-27-ips-flat-monitor-1920x1080-75hz-max-refresh-rate-5ms-gtg-fully-ergonomic-stand-usb-type-c-with", "url": "https://www.vuugo.com/product/samsung-ls27a400ujnxza-27-ls27a400ujnxza/", "retailer": "Vuugo", "category": "monitors", "currentPrice": 355.6, "minPrice": 355.6, "maxPrice": 355.6, "priceCount": 1, "firstSeen": "2026-03-23T04:44:25", "lastUpdated": "2026-03-23T04:44:25", "matchGroup": null, "canonicalId": null, "upc": "", "mpn": "", "priceComparison": []}