{"id": 159951, "name": "SanDisk USB Extreme PRO Dual Drive Flash Drive 1TB", "shortName": "SanDisk USB Extreme PRO Dual Drive Flash Drive 1TB", "imageUrl": "https://c1.neweggimages.com/productimage/nb300/BGH6S2507050B22LO4A.jpg", "brand": "SanDisk", "description": "SanDisk Extreme PRO 1TB dual-drive USB flash drive for high-speed portable storage.", "specs": {"capacity": "1TB", "type": "USB flash drive", "model": "Extreme PRO", "interface": "dual drive"}, "slug": "sandisk-usb-extreme-pro-dual-drive-flash-drive-1tb", "url": "https://www.newegg.ca/p/1BK-005K-000G7", "retailer": "Newegg Canada", "category": "external-storage", "currentPrice": 370.39, "minPrice": 370.39, "maxPrice": 370.39, "priceCount": 1, "firstSeen": "2026-03-15T04:16:42", "lastUpdated": "2026-03-15T04:16:42", "matchGroup": null, "canonicalId": 12781, "upc": "", "mpn": "USB-EXTREME-PRO-DUAL-DRIVE", "priceComparison": []}