{"id": 161884, "name": "TP-Link OMADA 8-PORT 10G MULTI-GIGABIT SWITCH PORT: 8 10G RJ45 PORTSSPEC: 1U 13-INCH RACK-MOUNTABLE STEEL CASE FEATURE: PLUG AND PLAY", "shortName": "TP-Link OMADA 8-PORT 10G MULTI-GIGABIT SWITCH PORT: 8 10G RJ45", "imageUrl": "https://c1.neweggimages.com/productimage/nb300/A1K6S2409040F34FH7D.jpg", "brand": "TP-Link", "description": "8-port 10G multi-gigabit rack-mountable managed switch for high-speed network connectivity.", "specs": {"ports": 8, "type": "10G multi-gigabit", "form_factor": "rack-mountable", "managed": true}, "slug": "tp-link-omada-8-port-10g-multi-gigabit-switch-port-8-10g-rj45-portsspec-1u-13-inch-rack-mountable-steel-case-feature-plu", "url": "https://www.newegg.ca/p/0XP-001U-008U1", "retailer": "Newegg Canada", "category": "network-switches", "currentPrice": 970.99, "minPrice": 970.99, "maxPrice": 970.99, "priceCount": 1, "firstSeen": "2026-03-15T04:28:17", "lastUpdated": "2026-03-15T04:28:17", "matchGroup": null, "canonicalId": 15645, "upc": "", "mpn": "", "priceComparison": []}