{"id": 464669, "name": "V277U Gbmiipx 27H 16:9 4ms (GTG) 350nits 2xHDMI 1xDP SPK Audio out HDR 10 AdaptiveSync US PA PA Black H.cable x1", "shortName": "V277U Gbmiipx 27H 16:9 4ms (GTG) 350nits 2xHDMI 1xDP SPK Audio out", "imageUrl": "", "brand": "V277U", "description": "", "specs": {}, "slug": "v277u-gbmiipx-27h-169-4ms-gtg-350nits-2xhdmi-1xdp-spk-audio-out-hdr-10-adaptivesync-us-pa-pa-black-hcable-x1", "url": "https://www.canadacomputers.com/en/monitors/277413/v277u-gbmiipx-27h-16-9-4ms-gtg-350nits-2xhdmi-1xdp-spk-audio-out-hdr-10-adaptivesync-us-pa-pa-black-h-cable-x1-umhv7aag05.html", "retailer": "Canada Computers", "category": "monitors", "currentPrice": 265.64, "minPrice": 265.64, "maxPrice": 265.64, "priceCount": 1, "firstSeen": "2026-03-25T06:27:05", "lastUpdated": "2026-03-25T06:27:05", "matchGroup": null, "canonicalId": null, "upc": "", "mpn": "", "priceComparison": []}