{"id": 54012, "name": "ViewSonic VX3218-PC-MHD 32 Inch Full HD 1080p 165Hz 1ms Curved Gaming Computer Monitor with Adaptive-Sync Eye Care Frameless HDMI and Display Port", "shortName": "ViewSonic VX3218-PC-MHD 32 Inch Full HD 1080p 165Hz 1ms Curved Gaming", "imageUrl": "https://c1.neweggimages.com/productimage/nb300/24-117-055-V01.jpg", "brand": "(3)", "description": "32-inch Full HD 165Hz curved gaming monitor with 1ms response time and eye care features for immersive gaming.", "specs": {"size": "32\"", "resolution": "1920x1080", "panel_type": "unknown", "refresh_rate": "165Hz", "response_time": "1ms", "features": "Curved, Adaptive-Sync, Eye Care"}, "slug": "viewsonic-vx3218-pc-mhd-32-inch-full-hd-1080p-165hz-1ms-curved-gaming-computer-monitor-with-adaptive-sync-eye-care-frame", "url": "https://www.newegg.ca/viewsonic-vx3218-pc-mhd-32-fhd-165-hz-va-black/p/N82E16824117055", "retailer": "Newegg Canada", "category": "monitors", "currentPrice": 254.99, "minPrice": 254.99, "maxPrice": 254.99, "priceCount": 2, "firstSeen": "2026-03-10T04:40:46", "lastUpdated": "2026-03-11T16:03:23", "matchGroup": null, "canonicalId": 6483, "upc": "", "mpn": "VX3218-PC-MHD", "priceComparison": []}