{"id": 52625, "name": "Wicked Audio Rad Rascal Wired Kid Safe Headphones - Sky Blue/Slime", "shortName": "Wicked Audio Rad Rascal Wired Kid Safe Headphones - Sky Blue/Slime", "imageUrl": "https://c1.neweggimages.com/productimage/nb300/0SD-00RZ-00011-Z01.jpg", "brand": "(2)", "description": "Wired kid-safe headphones with volume limiting, designed for children's protected listening.", "specs": {"type": "wired headphones", "model": "Rad Rascal", "target_audience": "kids", "safety_feature": "kid safe", "color": "sky blue/slime"}, "slug": "wicked-audio-rad-rascal-wired-kid-safe-headphones-sky-blueslime", "url": "https://www.newegg.ca/sky-blue-slime-wicked-wi311-on-ear/p/0SD-00RZ-00011", "retailer": "Newegg Canada", "category": "headphones", "currentPrice": 23.22, "minPrice": 23.22, "maxPrice": 23.22, "priceCount": 2, "firstSeen": "2026-03-10T04:35:44", "lastUpdated": "2026-03-11T15:58:13", "matchGroup": null, "canonicalId": 12416, "upc": "", "mpn": "RAD-RASCAL", "priceComparison": []}