{"id": 8318, "name": "Wireless gaming keyboard and mouse combination, with rainbow LED backlight, rechargeable waterproof mechanical dustproof 7-color backlight, suitable for laptops, PC gamers", "shortName": "Wireless gaming keyboard and mouse combination, with rainbow LED", "imageUrl": "https://c1.neweggimages.com/productimage/nb300/AR57S201008ssU9l.jpg", "brand": "(3)", "description": "Rechargeable wireless gaming keyboard and mouse combo with 7-color backlight and water-resistant design.", "specs": {"type": "combo", "connection": "wireless", "backlit": "7-color", "rechargeable": true, "water_resistant": true}, "slug": "wireless-gaming-keyboard-and-mouse-combination-with-rainbow-led-backlight-rechargeable-waterproof-mechanical-dustproof-7", "url": "https://www.newegg.ca/p/32N-00SS-00002", "retailer": "Newegg Canada", "category": "keyboards", "currentPrice": 159.2, "minPrice": 158.06, "maxPrice": 159.2, "priceCount": 9, "firstSeen": "2026-03-08T13:03:17", "lastUpdated": "2026-03-15T03:44:05", "matchGroup": null, "canonicalId": 13222, "upc": "", "mpn": "", "priceComparison": []}